json_work_manager/__init__.py
json_work_manager/json_work_manager.py
json_work_manager-0.0.14.dist-info/METADATA
json_work_manager-0.0.14.dist-info/WHEEL
json_work_manager-0.0.14.dist-info/top_level.txt
json_work_manager-0.0.14.dist-info/RECORD
