Metadata-Version: 2.1
Name: json-work-manager
Version: 0.0.14
Summary: Json work manager
Home-page: https://github.com/automatethem/json-work-manager
Author: Sang Ki Kwon
Author-email: automatethem@gmail.com
License: MIT
Requires-Dist: python-supporter
Requires-Dist: ai-supporter
